Metadata-Version: 2.1
Name: maths-operations-package
Version: 0.3
Summary: Basic maths operations implementations
Home-page: https://github.com/Snigdha2005/math_operations
Author: Snigdha
Author-email: YS.Snigdha@iiitb.com
License: IIITB
Platform: UNKNOWN
